MANIFEST.in
README.md
RELEASE-VERSION
setup.py
version.py
many_stop_words/__init__.py
many_stop_words/stopwords-en.txt
many_stop_words/stopwords-es.txt
many_stop_words/stopwords-it.txt
many_stop_words/stopwords-pt.txt
many_stop_words.egg-info/PKG-INFO
many_stop_words.egg-info/SOURCES.txt
many_stop_words.egg-info/dependency_links.txt
many_stop_words.egg-info/top_level.txt
many_stop_words/tests/__init__.py
many_stop_words/tests/test_many_stop_words.py